{
  "appId": "com.vtaper.coach",
  "appName": "V-Taper Coach",
  "webDir": "dist",
  "bundledWebRuntime": false,
  "server": {
    "androidScheme": "https",
    "hostname": "vtaper-coach.vercel.app"
  },
  "plugins": {
    "SplashScreen": {
      "launchShowDuration": 2000,
      "backgroundColor": "#0f172a",
      "androidSplashResourceName": "splash",
      "showSpinner": false,
      "launchAutoHide": true,
      "splashFullScreen": true,
      "splashImmersive": true
    },
    "StatusBar": {
      "style": "Dark",
      "backgroundColor": "#0f172a",
      "overlaysWebView": false
    },
    "PushNotifications": {
      "presentationOptions": ["badge", "sound", "alert"]
    },
    "Camera": {
      "allowEditing": true,
      "saveToGallery": true,
      "promptLabelPhoto": "Fotoğraf Seç",
      "promptLabelPicture": "Fotoğraf Çek"
    },
    "Haptics": {
      "enabled": true
    }
  },
  "android": {
    "backgroundColor": "#0f172a",
    "allowMixedContent": true,
    "webContentsDebuggingEnabled": false
  },
  "ios": {
    "contentInset": "automatic",
    "backgroundColor": "#0f172a",
    "allowsLinkPreview": false,
    "scrollEnabled": true
  }
}
